epigraph/__init__.py
epigraph/graphql_api.py
epigraph/introspection.py
epigraph/schema.py
epigraph/test_epigraph.py
epigraph/utilities.py
epigraph-2021.2.dist-info/LICENSE
epigraph-2021.2.dist-info/WHEEL
epigraph-2021.2.dist-info/METADATA
epigraph-2021.2.dist-info/RECORD
