Metadata-Version: 2.1
Name: epigraph
Version: 2021.2
Summary: Python API for graphql
Home-page: https://github.com/CHIMEFRB/epigraph
License: MIT
Author: Shiny Brar
Author-email: charanjotbrar@gmail.com
Requires-Python: >=3.6,<4.0
Classifier: Development Status :: 4 - Beta
Classifier: Intended Audience :: Developers
Classifier: Intended Audience :: Education
Classifier: Intended Audience :: Science/Research
Classifier: License :: OSI Approved :: MIT License
Classifier: Programming Language :: Python :: 3
Classifier: Programming Language :: Python :: 3.6
Classifier: Programming Language :: Python :: 3.7
Classifier: Programming Language :: Python :: 3.8
Classifier: Topic :: Scientific/Engineering :: Astronomy
Classifier: Topic :: Software Development :: Libraries :: Python Modules
Requires-Dist: graphqlclient (>=0.2,<0.3)
Requires-Dist: mkdocs-material (>=5.5.0,<6.0.0)
Project-URL: Documentation, https://github.com/CHIMEFRB/epigraph
Project-URL: Repository, https://github.com/CHIMEFRB/epigraph
